CHANGELOG.md
pydantricks-0.1.1.dist-info/METADATA
pydantricks-0.1.1.dist-info/WHEEL
pydantricks-0.1.1.dist-info/entry_points.txt
pydantricks-0.1.1.dist-info/licenses/LICENSE
pydantricks/__init__.py
pydantricks/field_factory.py
pydantricks/model_factory.py
pydantricks/py.typed
pydantricks/shared_utils/__init__.py
pydantricks/shared_utils/infer.py
pydantricks-0.1.1.dist-info/RECORD
